setup.py
djangoes/__init__.py
djangoes.egg-info/PKG-INFO
djangoes.egg-info/SOURCES.txt
djangoes.egg-info/dependency_links.txt
djangoes.egg-info/entry_points.txt
djangoes.egg-info/top_level.txt
djangoes/backends/__init__.py
djangoes/backends/abstracts.py
djangoes/backends/elasticsearch.py
djangoes/test/__init__.py
djangoes/test/mixins.py
djangoes/test/pytest.py
djangoes/test/runner.py
djangoes/test/testcases.py
djangoes/test/utils.py