Metadata-Version: 1.1
Name: djangoes
Version: 0.3.0
Summary: A way to integrate ElasticSearch into a Django project. No, this is not an ElasticSearch based ORM.
Home-page: https://github.com/exirel/djangoes/
Author: Florian Strzelecki
Author-email: florian.strzelecki@gmail.com
License: CC0 1.0 Universal (CC0 1.0) Public Domain Dedication
Keywords: django elasticsearch pytest
Platform: UNKNOWN
Classifier: Development Status :: 3 - Alpha
Classifier: Environment :: Plugins
Classifier: Environment :: Web Environment
Classifier: Framework :: Django
Classifier: Intended Audience :: Developers
Classifier: License :: CC0 1.0 Universal (CC0 1.0) Public Domain Dedication
Classifier: Operating System :: OS Independent
Classifier: Programming Language :: Python :: 3.4
Classifier: Programming Language :: Python :: 3 :: Only
Classifier: Topic :: Software Development :: Libraries :: Python Modules
